antimatter_api/__init__.py
antimatter_api/api_client.py
antimatter_api/api_response.py
antimatter_api/configuration.py
antimatter_api/exceptions.py
antimatter_api/py.typed
antimatter_api/rest.py
antimatter_api/api/__init__.py
antimatter_api/api/account_management_api.py
antimatter_api/api/authentication_api.py
antimatter_api/api/capsules_api.py
antimatter_api/api/contexts_api.py
antimatter_api/api/encryption_api.py
antimatter_api/api/general_api.py
antimatter_api/api/internal_api.py
antimatter_api/api/keychain_api.py
antimatter_api/api/policy_api.py
antimatter_api/models/__init__.py
antimatter_api/models/access_log_entry.py
antimatter_api/models/access_log_entry_create_info.py
antimatter_api/models/access_log_entry_open_info.py
antimatter_api/models/access_log_entry_read_info.py
antimatter_api/models/access_log_results.py
antimatter_api/models/active_root_encryption_key_id.py
antimatter_api/models/active_root_encryption_key_response.py
antimatter_api/models/add_capsule_log_entry_request.py
antimatter_api/models/add_read_context.py
antimatter_api/models/add_write_context.py
antimatter_api/models/antimatter_delegated_aws_key_info.py
antimatter_api/models/antimatter_delegated_azure_key_info.py
antimatter_api/models/antimatter_delegated_gcp_key_info.py
antimatter_api/models/api_key_domain_identity_provider_details.py
antimatter_api/models/available_delegated_root_encryption_key_provider.py
antimatter_api/models/available_root_encryption_key_providers.py
antimatter_api/models/available_root_encryption_key_providers_providers_inner.py
antimatter_api/models/available_service_account_root_encryption_key_provider.py
antimatter_api/models/aws_service_account_key_info.py
antimatter_api/models/azure_service_account_key_info.py
antimatter_api/models/byok_key_info.py
antimatter_api/models/capability.py
antimatter_api/models/capability_definition.py
antimatter_api/models/capability_definition_list.py
antimatter_api/models/capability_expression.py
antimatter_api-2.0.13.dist-info/METADATA
antimatter_api-2.0.13.dist-info/WHEEL
antimatter_api-2.0.13.dist-info/top_level.txt
antimatter_api-2.0.13.dist-info/RECORD
