Metadata-Version: 2.1
Name: antimatter-api
Version: 2.0.13
Summary: Antimatter Public API
Home-page: 
Author: OpenAPI Generator community
Author-email: support@antimatter.io
License: Apache-2.0
Keywords: OpenAPI,OpenAPI-Generator,Antimatter Public API
Requires-Dist: urllib3 <3.0.0,>=1.25.3
Requires-Dist: python-dateutil >=2.8.2
Requires-Dist: pydantic >=2
Requires-Dist: typing-extensions >=4.7.1
